mushare/__init__.py
mushare/bond/__init__.py
mushare/bond/bonds.py
mushare/coins/__init__.py
mushare/coins/market.py
mushare/data/__init__.py
mushare/fund/__init__.py
mushare/fund/cons.py
mushare/fund/nav.py
mushare/futures/__init__.py
mushare/futures/cons.py
mushare/futures/domestic.py
mushare/futures/domestic_cons.py
mushare/futures/intlfutures.py
mushare/internet/__init__.py
mushare/internet/boxoffice.py
mushare/internet/caixinnews.py
mushare/internet/indexes.py
mushare/pro/__init__.py
mushare/pro/client.py
mushare/pro/data_pro.py
mushare/stock/__init__.py
mushare/stock/billboard.py
mushare/stock/classifying.py
mushare/stock/cons.py
mushare/stock/fundamental.py
mushare/stock/globals.py
mushare/stock/indictor.py
mushare/stock/macro.py
mushare/stock/macro_vars.py
mushare/stock/minsdata.py
mushare/stock/news_vars.py
mushare/stock/newsevent.py
mushare/stock/ref_vars.py
mushare/stock/reference.py
mushare/stock/shibor.py
mushare/stock/trading.py
mushare/subs/__init__.py
mushare/subs/ts_subs.py
mushare/subs/ht_subs/__init__.py
mushare/subs/ht_subs/service/__init__.py
mushare/subs/ht_subs/service/covert.py
mushare/subs/model/__init__.py
mushare/subs/model/min.py
mushare/subs/model/tick.py
mushare/trader/__init__.py
mushare/trader/trader.py
mushare/trader/utils.py
mushare/trader/vars.py
mushare/util/__init__.py
mushare/util/common.py
mushare/util/conns.py
mushare/util/dateu.py
mushare/util/formula.py
mushare/util/mailmerge.py
mushare/util/netbase.py
mushare/util/store.py
mushare/util/upass.py
mushare/util/vars.py
mushare/util/protobuf/__init__.py
mushare/util/protobuf/funcs.py
mushare/util/protobuf/response_pb2.py
mushare-0.0.3.dist-info/LICENSE
mushare-0.0.3.dist-info/METADATA
mushare-0.0.3.dist-info/WHEEL
mushare-0.0.3.dist-info/top_level.txt
mushare-0.0.3.dist-info/RECORD
